flask_shopify_utils/__init__.py
flask_shopify_utils/model.py
flask_shopify_utils/utils.py
Flask_ShopifyUtils-0.0.3.dist-info/LICENSE
Flask_ShopifyUtils-0.0.3.dist-info/METADATA
Flask_ShopifyUtils-0.0.3.dist-info/WHEEL
Flask_ShopifyUtils-0.0.3.dist-info/top_level.txt
Flask_ShopifyUtils-0.0.3.dist-info/RECORD
