Metadata-Version: 2.1
Name: Flask-ShopifyUtils
Version: 0.0.3
Summary: Some utils for Shopify that could be use in Flask
Home-page: https://github.com/leocxy/flask-shopify-utils
Author: Leo Chen
Author-email: leo.cxy88@gmail.com
License: MIT
Classifier: Programming Language :: Python :: 3
Classifier: License :: OSI Approved :: MIT License
Classifier: Operating System :: OS Independent
Classifier: Development Status :: 3 - Alpha
Requires-Python: >=3.8
License-File: LICENSE
Requires-Dist: Flask (<3)
Requires-Dist: Flask-SQLAlchemy (==3.0.5)
Requires-Dist: ShopifyAPI (==12.3.0)
Requires-Dist: sgqlc (<17)
Requires-Dist: psutil (==5.9.5)
Requires-Dist: pytz (==2023.3)
Requires-Dist: requests (<3)
Requires-Dist: Cerberus (==1.3.4)
Requires-Dist: PyJWT (==2.7.0)
